witness/__init__.py
witness/version.py
witness/core/__init__.py
witness/core/abstract.py
witness/core/batch.py
witness/core/meta.py
witness/extractors/__init__.py
witness/extractors/database.py
witness/extractors/file.py
witness/extractors/http.py
witness/loaders/__init__.py
witness/loaders/file.py
witness/providers/__init__.py
witness/providers/pandas/__init__.py
witness/providers/pandas/core.py
witness/providers/pandas/extractors.py
witness/providers/pandas/loaders.py
witness/serializers/__init__.py
witness/serializers/common.py
witness_etl-0.0.9.dist-info/LICENSE
witness_etl-0.0.9.dist-info/METADATA
witness_etl-0.0.9.dist-info/WHEEL
witness_etl-0.0.9.dist-info/top_level.txt
witness_etl-0.0.9.dist-info/RECORD
