Metadata-Version: 2.1
Name: witness-etl
Version: 0.0.9
Summary: A minimal ETL library.
Author: Eugene Popov
Author-email: evgeniypalych@gmail.com
License: Apache License 2.0
Project-URL: Source Code, https://github.com/eppv/witness
Classifier: Intended Audience :: Developers
Classifier: Programming Language :: Python :: 3.9
Classifier: License :: OSI Approved :: Apache Software License
Classifier: Operating System :: OS Independent
Requires-Python: >=3.9
License-File: LICENSE
Requires-Dist: pyarrow >=12.0.0
Requires-Dist: pyodbc >=4.0.0
Requires-Dist: pandas <2.0,>=1.4.0
Requires-Dist: sqlalchemy <2.0,>=1.4.0
Requires-Dist: requests >=2.28.0
Requires-Dist: pendulum >=2.1.0
Requires-Dist: numpy >=1.23.0 ; python_version >= "3.9"
